servodoor/__init__.py
servodoor/servodoor.py
servodoor-0.1.0.dist-info/LICENSE.txt
servodoor-0.1.0.dist-info/METADATA
servodoor-0.1.0.dist-info/WHEEL
servodoor-0.1.0.dist-info/RECORD
