Metadata-Version: 2.1
Name: servodoor
Version: 0.1.0
Summary: A simple library for controlling RC servo based doors
Home-page: https://github.com/willdickson/servodoor
License: MIT
Author: Will Dickson
Author-email: wbd@caltech.edu
Requires-Python: >=3.10,<3.12
Classifier: Development Status :: 3 - Alpha
Classifier: Intended Audience :: Science/Research
Classifier: License :: OSI Approved :: MIT License
Classifier: Programming Language :: Python :: 3
Classifier: Programming Language :: Python :: 3.10
Classifier: Programming Language :: Python :: 3.11
Requires-Dist: pyserial (>=3.5,<4.0)
Project-URL: Repository, https://github.com/willdickson/servodoor
